predictions_lib_mk/__init__.py
predictions_lib_mk/model_utils.py
predictions_lib_mk-0.1.dist-info/METADATA
predictions_lib_mk-0.1.dist-info/WHEEL
predictions_lib_mk-0.1.dist-info/top_level.txt
predictions_lib_mk-0.1.dist-info/RECORD
