Metadata-Version: 2.1
Name: predictions_lib_mk
Version: 0.1
Summary: Lib for NN predictions CNN based v1
Author: Martin Kuba
